lzss/__init__.py
lzss/lzss.py
lzss/version.py
lzss_python-0.0.2.dist-info/WHEEL
lzss_python-0.0.2.dist-info/METADATA
lzss_python-0.0.2.dist-info/licenses/LICENSE
lzss_python-0.0.2.dist-info/RECORD
