Metadata-Version: 2.1
Name: lzss-python
Version: 0.0.2
Summary: A Python LZSS implementation.
License: MIT
Author: Tim Cogan
Requires-Python: >=3.10
